README
setup.cfg
setup.py
messenger/__init__.py
messenger/const.py
messenger/exceptions.py
messenger/models/__init__.py
messenger/models/attachment.py
messenger/models/bot.py
messenger/models/button.py
messenger/models/quick_replies.py
messenger/models/templates.py
python_messenger.egg-info/PKG-INFO
python_messenger.egg-info/SOURCES.txt
python_messenger.egg-info/dependency_links.txt
python_messenger.egg-info/top_level.txt