Metadata-Version: 1.1
Name: python-messenger
Version: 0.1.2
Summary: Bot class for Facebook Messenger
Home-page: https://github.com/akoskaaa/python-messenger
Author: Akos Hochrein
Author-email: hoch.akos@gmail.com
License: Apache License 2.0
Download-URL: https://github.com/akoskaaa/python-messenger/tarball/0.1
Keywords: messenger,chat,bot,chatbot
Platform: UNKNOWN
